battalion/__init__.py
battalion/api.py
battalion/autodoc.py
battalion/base.py
battalion/command.py
battalion/exceptions.py
battalion/handler.py
battalion/log.py
battalion/registry.py
battalion/state.py
battalion/utils.py
battalion-0.5.6.dist-info/DESCRIPTION.rst
battalion-0.5.6.dist-info/LICENSE.txt
battalion-0.5.6.dist-info/METADATA
battalion-0.5.6.dist-info/RECORD
battalion-0.5.6.dist-info/WHEEL
battalion-0.5.6.dist-info/metadata.json
battalion-0.5.6.dist-info/pbr.json
battalion-0.5.6.dist-info/top_level.txt
