Metadata-Version: 2.0
Name: battalion
Version: 0.5.6
Summary: Python framework for commandline applications
Home-page: UNKNOWN
Author: Kyle Rockman
Author-email: ['kyle.rockman@mac.com']
License: UNKNOWN
Platform: UNKNOWN
Requires-Dist: docopt (==0.6.2)
Requires-Dist: pyul (==0.4.5)
Requires-Dist: pyversion (==0.5.5)
Requires-Dist: six (==1.9.0)
